netbox_mikrotik-0.1.0.dev1.dist-info/METADATA
netbox_mikrotik-0.1.0.dev1.dist-info/WHEEL
netbox_mikrotik-0.1.0.dev1.dist-info/entry_points.txt
netbox_mikrotik-0.1.0.dev1.dist-info/licenses/LICENSE
netbox_mikrotik/__init__.py
netbox_mikrotik-0.1.0.dev1.dist-info/RECORD
