Metadata-Version: 2.1
Name: netbox-mikrotik
Version: 0.1.0.dev1
Summary: Sync IP-Adresses to Mikrotik Adress Lists and more.
Author-Email: Julius Koenig <info@bastelquartier.de>
License:                     GNU GENERAL PUBLIC LICENSE
Requires-Python: >=3.10
